ecp/__init__.py
ecp-0.0.2.dist-info/METADATA
ecp-0.0.2.dist-info/RECORD
ecp-0.0.2.dist-info/WHEEL
ecp-0.0.2.dist-info/top_level.txt
